xrpl_helpers/common/utils.py
xrpl_helpers/genesis.xahau.json
xrpl_helpers/genesis.xrpl.json
xrpl_helpers/libs/google/storage.py
xrpl_helpers/rippled/utils.py
xrpl_helpers/sdk/hooks.py
xrpl_helpers/sdk/utils.py
xrpl_helpers-1.0.6.dist-info/METADATA
xrpl_helpers-1.0.6.dist-info/WHEEL
xrpl_helpers-1.0.6.dist-info/RECORD
